sentry_nodestore_opensearch/__init__.py
sentry_nodestore_opensearch/backend.py
sentry_nodestore_opensearch-1.0.1.dist-info/licenses/LICENSE
sentry_nodestore_opensearch-1.0.1.dist-info/METADATA
sentry_nodestore_opensearch-1.0.1.dist-info/WHEEL
sentry_nodestore_opensearch-1.0.1.dist-info/top_level.txt
sentry_nodestore_opensearch-1.0.1.dist-info/RECORD
