Metadata-Version: 2.4
Name: sentry-nodestore-opensearch
Version: 1.0.1
Summary: Sentry nodestore OpenSearch backend
Home-page: https://github.com/wedeploy/sentry-nodestore-opensearch
Author: info@wedeploy.pl
Author-email: info@wedeploy.pl
License: Apache-2.0
Project-URL: Bug Tracker, https://github.com/wedeploy/sentry-nodestore-opensearch/issues
Project-URL: CI, https://github.com/wedeploy/sentry-nodestore-opensearch/actions
Project-URL: Source Code, https://github.com/wedeploy/sentry-nodestore-opensearch
Keywords: sentry,opensearch,nodestore,backend
Classifier: Development Status :: 5 - Production/Stable
Classifier: Intended Audience :: Developers
Classifier: License :: OSI Approved :: Apache Software License
Classifier: Operating System :: POSIX
Classifier: Operating System :: MacOS :: MacOS X
Classifier: Operating System :: Microsoft :: Windows
Classifier: Programming Language :: Python
Classifier: Operating System :: OS Independent
License-File: LICENSE
Requires-Dist: opensearch-py==2.*
Dynamic: author
Dynamic: author-email
Dynamic: classifier
Dynamic: description
Dynamic: description-content-type
Dynamic: home-page
Dynamic: keywords
Dynamic: license
Dynamic: license-file
Dynamic: project-url
Dynamic: requires-dist
Dynamic: summary
